etri_klesa_text_writer/__init__.py
etri_klesa_text_writer-0.1.1.dist-info/METADATA
etri_klesa_text_writer-0.1.1.dist-info/WHEEL
etri_klesa_text_writer-0.1.1.dist-info/entry_points.txt
etri_klesa_text_writer-0.1.1.dist-info/RECORD
